[
  {
    "brand": "Travis Mathew",
    "scraped_at": "2025-11-14T22:03:27.617Z",
    "is_homepage_product": false,
    "category": "Tops",
    "gender": "Men",
    "currency": "USD",
    "colors": [
      "Dark Olive",
      "Total Eclipse/Apricot",
      "Birch",
      "Bering Sea/Sleet"
    ],
    "sizes": [],
    "fabrics": [],
    "url": "https://travismathew.com/collections/mens-button-ups/products/cloud-flannel-plaid-button-up?variant=42938794115150",
    "product_id": "cloud-flannel-plaid-button-up/",
    "name": "Cloud Flannel Plaid Button-Up",
    "price": 139.95,
    "sale_price": null,
    "on_sale": false,
    "images": [
      "https://cdn.shopify.com/s/files/1/0610/4629/2558/files/1MZ383_3DOL_1_ECOMM_97bb9cd8-9394-4b42-970e-80c1c4c4a5e1.jpg"
    ],
    "badges": [],
    "sku": "cloud-flannel-plaid-button-up/"
  },
  {
    "brand": "Travis Mathew",
    "scraped_at": "2025-11-14T22:03:27.618Z",
    "is_homepage_product": false,
    "category": "Tops",
    "gender": "Men",
    "currency": "USD",
    "colors": [
      "Birch",
      "Dark Olive",
      "Total Eclipse/Apricot",
      "Bering Sea/Sleet"
    ],
    "sizes": [],
    "fabrics": [],
    "url": "https://travismathew.com/collections/mens-button-ups/products/cloud-flannel-plaid-button-up?variant=43059395362894",
    "product_id": "cloud-flannel-plaid-button-up/",
    "name": "Cloud Flannel Plaid Button-Up",
    "price": 139.95,
    "sale_price": null,
    "on_sale": false,
    "images": [
      "https://cdn.shopify.com/s/files/1/0610/4629/2558/files/1MZ383_A0007_1_ECOMM_c6a11a7d-c996-4cd9-b7e2-b5af681e2db6.jpg"
    ],
    "badges": [],
    "sku": "cloud-flannel-plaid-button-up/"
  },
  {
    "brand": "Travis Mathew",
    "scraped_at": "2025-11-14T22:03:27.618Z",
    "is_homepage_product": false,
    "category": "Tops",
    "gender": "Men",
    "currency": "USD",
    "colors": [
      "Bering Sea/Sleet",
      "Dark Olive",
      "Total Eclipse/Apricot",
      "Birch"
    ],
    "sizes": [],
    "fabrics": [],
    "url": "https://travismathew.com/collections/mens-button-ups/products/cloud-flannel-plaid-button-up?variant=43059395592270",
    "product_id": "cloud-flannel-plaid-button-up/",
    "name": "Cloud Flannel Plaid Button-Up",
    "price": 139.95,
    "sale_price": null,
    "on_sale": false,
    "images": [
      "https://cdn.shopify.com/s/files/1/0610/4629/2558/files/1MZ383_Q1161_1_ECOMM_26741cb9-86c8-4a6e-aba0-88b9d334b79d.jpg"
    ],
    "badges": [],
    "sku": "cloud-flannel-plaid-button-up/"
  },
  {
    "brand": "Travis Mathew",
    "scraped_at": "2025-11-14T22:03:27.619Z",
    "is_homepage_product": false,
    "category": "Tops",
    "gender": "Men",
    "currency": "USD",
    "colors": [
      "Oxford Tan",
      "Black",
      "Heather Light Grey",
      "Dark Olive",
      "Bering Sea"
    ],
    "sizes": [],
    "fabrics": [],
    "url": "https://travismathew.com/collections/mens-button-ups/products/cloud-waffle-shirt-jacket?variant=42763778687054",
    "product_id": "cloud-waffle-shirt-jacket/",
    "name": "Cloud Waffle Shirt Jacket",
    "price": 179.95,
    "sale_price": null,
    "on_sale": false,
    "images": [
      "https://cdn.shopify.com/s/files/1/0610/4629/2558/files/A42698_2OFT_1_ECOMM_3b02da71-631f-4051-ab91-96bd3f0ec7da.jpg"
    ],
    "badges": [],
    "sku": "cloud-waffle-shirt-jacket/"
  },
  {
    "brand": "Travis Mathew",
    "scraped_at": "2025-11-14T22:03:27.619Z",
    "is_homepage_product": false,
    "category": "Tops",
    "gender": "Men",
    "currency": "USD",
    "colors": [
      "Bering Sea",
      "Black",
      "White"
    ],
    "sizes": [],
    "fabrics": [],
    "url": "https://travismathew.com/collections/mens-button-ups/products/techwoven-tidbits-button-up?variant=42659619733582",
    "product_id": "techwoven-tidbits-button-up/",
    "name": "Techwoven Tidbits Button-Up",
    "price": 139.95,
    "sale_price": null,
    "on_sale": false,
    "images": [
      "https://cdn.shopify.com/s/files/1/0610/4629/2558/files/A42271_C0574_1_ECOMM-jpg_efaedbc5-87bb-4f3a-950c-bde65a29250c.jpg"
    ],
    "badges": [],
    "sku": "techwoven-tidbits-button-up/"
  },
  {
    "brand": "Travis Mathew",
    "scraped_at": "2025-11-14T22:03:27.619Z",
    "is_homepage_product": false,
    "category": "Tops",
    "gender": "Men",
    "currency": "USD",
    "colors": [
      "White",
      "Black",
      "Bering Sea"
    ],
    "sizes": [],
    "fabrics": [],
    "url": "https://travismathew.com/collections/mens-button-ups/products/techwoven-tidbits-button-up?variant=42659619536974",
    "product_id": "techwoven-tidbits-button-up/",
    "name": "Techwoven Tidbits Button-Up",
    "price": 139.95,
    "sale_price": null,
    "on_sale": false,
    "images": [
      "https://cdn.shopify.com/s/files/1/0610/4629/2558/files/A42271_1WHT_1_ECOMM-jpg_630b4b7d-08b0-4e85-9ae8-365fb9040c77.jpg"
    ],
    "badges": [],
    "sku": "techwoven-tidbits-button-up/"
  },
  {
    "brand": "Travis Mathew",
    "scraped_at": "2025-11-14T22:03:27.620Z",
    "is_homepage_product": false,
    "category": "Tops",
    "gender": "Men",
    "currency": "USD",
    "colors": [
      "Black",
      "White",
      "Bering Sea"
    ],
    "sizes": [],
    "fabrics": [],
    "url": "https://travismathew.com/collections/mens-button-ups/products/techwoven-tidbits-button-up?variant=42659619340366",
    "product_id": "techwoven-tidbits-button-up/",
    "name": "Techwoven Tidbits Button-Up",
    "price": 139.95,
    "sale_price": null,
    "on_sale": false,
    "images": [
      "https://cdn.shopify.com/s/files/1/0610/4629/2558/files/A42271_0BLK_1_ECOMM-jpg_ebc374ec-c347-45fa-8804-970ff6ce5e73.jpg"
    ],
    "badges": [],
    "sku": "techwoven-tidbits-button-up/"
  },
  {
    "brand": "Travis Mathew",
    "scraped_at": "2025-11-14T22:03:27.620Z",
    "is_homepage_product": false,
    "category": "Tops",
    "gender": "Men",
    "currency": "USD",
    "colors": [
      "Black",
      "White",
      "Arona"
    ],
    "sizes": [],
    "fabrics": [],
    "url": "https://travismathew.com/collections/mens-button-ups/products/techwoven-country-mile-button-up?variant=43044744429646",
    "product_id": "techwoven-country-mile-button-up/",
    "name": "Techwoven Country Mile Button-Up",
    "price": 99.95,
    "sale_price": null,
    "on_sale": false,
    "images": [
      "https://cdn.shopify.com/s/files/1/0610/4629/2558/files/1MAA367_0BLK_ECOMM-JPG_2849364a-3c30-4571-b89b-7440950a7108.jpg"
    ],
    "badges": [],
    "sku": "techwoven-country-mile-button-up/"
  },
  {
    "brand": "Travis Mathew",
    "scraped_at": "2025-11-14T22:03:27.620Z",
    "is_homepage_product": false,
    "category": "Tops",
    "gender": "Men",
    "currency": "USD",
    "colors": [
      "Mood Indigo/Vintage Indigo",
      "Cory Blue",
      "Heather Rose Wine"
    ],
    "sizes": [],
    "fabrics": [],
    "url": "https://travismathew.com/collections/mens-button-ups/products/early-check-in-button-up?variant=42561851621454",
    "product_id": "early-check-in-button-up/",
    "name": "Early Check In Button-Up",
    "price": 119.95,
    "sale_price": null,
    "on_sale": false,
    "images": [
      "https://cdn.shopify.com/s/files/1/0610/4629/2558/files/A40213_4MIV_ECOMM_d29a9a4b-6386-4417-a9fe-dea52368e6d5.jpg"
    ],
    "badges": [],
    "sku": "early-check-in-button-up/"
  },
  {
    "brand": "Travis Mathew",
    "scraped_at": "2025-11-14T22:03:27.621Z",
    "is_homepage_product": false,
    "category": "Tops",
    "gender": "Men",
    "currency": "USD",
    "colors": [
      "Black",
      "Heather Light Grey",
      "Oxford Tan",
      "Dark Olive",
      "Bering Sea"
    ],
    "sizes": [],
    "fabrics": [],
    "url": "https://travismathew.com/collections/mens-button-ups/products/cloud-waffle-shirt-jacket?variant=42659612819534",
    "product_id": "cloud-waffle-shirt-jacket/",
    "name": "Cloud Waffle Shirt Jacket",
    "price": 179.95,
    "sale_price": null,
    "on_sale": false,
    "images": [
      "https://cdn.shopify.com/s/files/1/0610/4629/2558/files/A42698_0BLK_1_ECOMM.jpg"
    ],
    "badges": [],
    "sku": "cloud-waffle-shirt-jacket/"
  },
  {
    "brand": "Travis Mathew",
    "scraped_at": "2025-11-14T22:03:27.621Z",
    "is_homepage_product": false,
    "category": "Tops",
    "gender": "Men",
    "currency": "USD",
    "colors": [
      "Maple"
    ],
    "sizes": [],
    "fabrics": [],
    "url": "https://travismathew.com/collections/mens-button-ups/products/cloud-flannel-button-up?variant=43110061539406",
    "product_id": "cloud-flannel-button-up/",
    "name": "Cloud Flannel Button-Up",
    "price": 139.95,
    "sale_price": null,
    "on_sale": false,
    "images": [
      "https://cdn.shopify.com/s/files/1/0610/4629/2558/files/1MX435_D0088_1_ECOMM_cc2fc8d8-5373-43f1-9196-be5afaca7c27.jpg"
    ],
    "badges": [],
    "sku": "cloud-flannel-button-up/"
  },
  {
    "brand": "Travis Mathew",
    "scraped_at": "2025-11-14T22:03:27.621Z",
    "is_homepage_product": false,
    "category": "Tops",
    "gender": "Men",
    "currency": "USD",
    "colors": [
      "Heather Quiet Shade"
    ],
    "sizes": [],
    "fabrics": [],
    "url": "https://travismathew.com/collections/mens-button-ups/products/hefe-button-up?variant=43110036439118",
    "product_id": "hefe-button-up/",
    "name": "Hefe Button-Up",
    "price": 124.95,
    "sale_price": null,
    "on_sale": false,
    "images": [
      "https://cdn.shopify.com/s/files/1/0610/4629/2558/files/1MP221_0HQS_ECOMM_6eb6f0fc-b567-41e0-845e-505f84699842.jpg"
    ],
    "badges": [],
    "sku": "hefe-button-up/"
  },
  {
    "brand": "Travis Mathew",
    "scraped_at": "2025-11-14T22:03:27.622Z",
    "is_homepage_product": false,
    "category": "Tops",
    "gender": "Men",
    "currency": "USD",
    "colors": [
      "White",
      "Black",
      "Arona"
    ],
    "sizes": [],
    "fabrics": [],
    "url": "https://travismathew.com/collections/mens-button-ups/products/techwoven-country-mile-button-up?variant=43044744626254",
    "product_id": "techwoven-country-mile-button-up/",
    "name": "Techwoven Country Mile Button-Up",
    "price": 99.95,
    "sale_price": null,
    "on_sale": false,
    "images": [
      "https://cdn.shopify.com/s/files/1/0610/4629/2558/files/1MAA367_1WHT_ECOMM-JPG_bd6f4073-b4e2-42bb-936b-665b2f19d1c2.jpg"
    ],
    "badges": [],
    "sku": "techwoven-country-mile-button-up/"
  },
  {
    "brand": "Travis Mathew",
    "scraped_at": "2025-11-14T22:03:27.622Z",
    "is_homepage_product": false,
    "category": "Tops",
    "gender": "Men",
    "currency": "USD",
    "colors": [
      "Arona",
      "Black",
      "White"
    ],
    "sizes": [],
    "fabrics": [],
    "url": "https://travismathew.com/collections/mens-button-ups/products/techwoven-country-mile-button-up?variant=42561820098638",
    "product_id": "techwoven-country-mile-button-up/",
    "name": "Techwoven Country Mile Button-Up",
    "price": 99.95,
    "sale_price": null,
    "on_sale": false,
    "images": [
      "https://cdn.shopify.com/s/files/1/0610/4629/2558/files/1MAA367_3ARO_1_ECOMM_11a8c966-9f32-4d37-9342-c88ad6e359dd.jpg"
    ],
    "badges": [],
    "sku": "techwoven-country-mile-button-up/"
  },
  {
    "brand": "Travis Mathew",
    "scraped_at": "2025-11-14T22:03:27.622Z",
    "is_homepage_product": false,
    "category": "Tops",
    "gender": "Men",
    "currency": "USD",
    "colors": [
      "Pacific Coast"
    ],
    "sizes": [],
    "fabrics": [],
    "url": "https://travismathew.com/collections/mens-button-ups/products/canopy-breeze-button-up?variant=42565149884494",
    "product_id": "canopy-breeze-button-up/",
    "name": "Canopy Breeze Button-Up",
    "price": 109.95,
    "sale_price": null,
    "on_sale": false,
    "images": [
      "https://cdn.shopify.com/s/files/1/0610/4629/2558/files/A40216_C0453_1_ECOMM_065d0f54-d3f5-4293-ac45-d0a45e359a94.jpg"
    ],
    "badges": [],
    "sku": "canopy-breeze-button-up/"
  },
  {
    "brand": "Travis Mathew",
    "scraped_at": "2025-11-14T22:03:27.622Z",
    "is_homepage_product": false,
    "category": "Tops",
    "gender": "Men",
    "currency": "USD",
    "colors": [
      "Mood Indigo/Vintage Indigo"
    ],
    "sizes": [],
    "fabrics": [],
    "url": "https://travismathew.com/collections/mens-button-ups/products/knit-featherweight-night-button-up?variant=42565167743054",
    "product_id": "knit-featherweight-night-button-up/",
    "name": "Knit Featherweight Night Button-Up",
    "price": 119.95,
    "sale_price": null,
    "on_sale": false,
    "images": [
      "https://cdn.shopify.com/s/files/1/0610/4629/2558/files/A40243_4MIV_1_ECOMM_64ca3bf3-e7c7-4544-968b-69de66411efe.jpg"
    ],
    "badges": [],
    "sku": "knit-featherweight-night-button-up/"
  },
  {
    "brand": "Travis Mathew",
    "scraped_at": "2025-11-14T22:03:27.623Z",
    "is_homepage_product": false,
    "category": "Tops",
    "gender": "Men",
    "currency": "USD",
    "colors": [
      "Mood Indigo/Vintage Indigo"
    ],
    "sizes": [],
    "fabrics": [],
    "url": "https://travismathew.com/collections/mens-button-ups/products/knit-day-cruise-button-up?variant=42565152702542",
    "product_id": "knit-day-cruise-button-up/",
    "name": "Knit Day Cruise Button-Up",
    "price": 119.95,
    "sale_price": null,
    "on_sale": false,
    "images": [
      "https://cdn.shopify.com/s/files/1/0610/4629/2558/files/A40240_4MIV_1_ECOMM_574d488b-f2ce-4ea0-a86f-8225e816789e.jpg"
    ],
    "badges": [],
    "sku": "knit-day-cruise-button-up/"
  },
  {
    "brand": "Travis Mathew",
    "scraped_at": "2025-11-14T22:03:27.623Z",
    "is_homepage_product": false,
    "category": "Tops",
    "gender": "Men",
    "currency": "USD",
    "colors": [
      "Heather Rose Wine",
      "Mood Indigo/Vintage Indigo",
      "Cory Blue"
    ],
    "sizes": [],
    "fabrics": [],
    "url": "https://travismathew.com/collections/mens-button-ups/products/early-check-in-button-up?variant=42561851686990",
    "product_id": "early-check-in-button-up/",
    "name": "Early Check In Button-Up",
    "price": 119.95,
    "sale_price": null,
    "on_sale": false,
    "images": [
      "https://cdn.shopify.com/s/files/1/0610/4629/2558/files/A40213_J0150_ECOMM_bee58a90-b99c-4f4e-90c1-fc02d0099d0c.jpg"
    ],
    "badges": [],
    "sku": "early-check-in-button-up/"
  },
  {
    "brand": "Travis Mathew",
    "scraped_at": "2025-11-14T22:03:27.623Z",
    "is_homepage_product": false,
    "category": "Tops",
    "gender": "Men",
    "currency": "USD",
    "colors": [
      "Captains Blue"
    ],
    "sizes": [],
    "fabrics": [],
    "url": "https://travismathew.com/collections/mens-button-ups/products/techwoven-seamate-button-up?variant=42565170528334",
    "product_id": "techwoven-seamate-button-up/",
    "name": "Techwoven Seamate Button-Up",
    "price": 99.95,
    "sale_price": null,
    "on_sale": false,
    "images": [
      "https://cdn.shopify.com/s/files/1/0610/4629/2558/files/A42384_C0438_1_ECOMM_13d7808a-f103-409d-89d5-8cf360665114.jpg"
    ],
    "badges": [],
    "sku": "techwoven-seamate-button-up/"
  },
  {
    "brand": "Travis Mathew",
    "scraped_at": "2025-11-14T22:03:27.623Z",
    "is_homepage_product": false,
    "category": "Tops",
    "gender": "Men",
    "currency": "USD",
    "colors": [
      "Cory Blue",
      "Mood Indigo/Vintage Indigo",
      "Heather Rose Wine"
    ],
    "sizes": [],
    "fabrics": [],
    "url": "https://travismathew.com/collections/mens-button-ups/products/early-check-in-button-up?variant=42561851654222",
    "product_id": "early-check-in-button-up/",
    "name": "Early Check In Button-Up",
    "price": 119.95,
    "sale_price": null,
    "on_sale": false,
    "images": [
      "https://cdn.shopify.com/s/files/1/0610/4629/2558/files/A40213_C0441_1_ECOMM-jpg_f482419d-357c-4ad3-a1d1-69325f413cad.jpg"
    ],
    "badges": [],
    "sku": "early-check-in-button-up/"
  },
  {
    "brand": "Travis Mathew",
    "scraped_at": "2025-11-14T22:03:27.624Z",
    "is_homepage_product": false,
    "category": "Tops",
    "gender": "Men",
    "currency": "USD",
    "colors": [
      "Moonbeam"
    ],
    "sizes": [],
    "fabrics": [],
    "url": "https://travismathew.com/collections/mens-button-ups/products/something-new-button-up?variant=42425739345998",
    "product_id": "something-new-button-up/",
    "name": "Something New Button-Up",
    "price": 99.95,
    "sale_price": null,
    "on_sale": false,
    "images": [
      "https://cdn.shopify.com/s/files/1/0610/4629/2558/files/A40218_1MOB_ECOMM_93d86062-a7e0-4029-805a-c1fe1de29cfd.jpg"
    ],
    "badges": [],
    "sku": "something-new-button-up/"
  },
  {
    "brand": "Travis Mathew",
    "scraped_at": "2025-11-14T22:03:27.624Z",
    "is_homepage_product": false,
    "category": "Tops",
    "gender": "Men",
    "currency": "USD",
    "colors": [
      "White",
      "Black"
    ],
    "sizes": [],
    "fabrics": [],
    "url": "https://travismathew.com/collections/mens-button-ups/products/mist-on-the-lake-button-up?variant=42678121660494",
    "product_id": "mist-on-the-lake-button-up/",
    "name": "Mist On The Lake Button-Up",
    "price": 109.95,
    "sale_price": null,
    "on_sale": false,
    "images": [
      "https://cdn.shopify.com/s/files/1/0610/4629/2558/files/1MAA268_1WHT_1_ECOMM-jpg_beff8992-709b-4e2f-8fb3-09c9e68e7ce1.jpg"
    ],
    "badges": [],
    "sku": "mist-on-the-lake-button-up/"
  },
  {
    "brand": "Travis Mathew",
    "scraped_at": "2025-11-14T22:03:27.624Z",
    "is_homepage_product": false,
    "category": "Tops",
    "gender": "Men",
    "currency": "USD",
    "colors": [
      "Dark Olive",
      "Black",
      "Heather Light Grey",
      "Oxford Tan",
      "Bering Sea"
    ],
    "sizes": [],
    "fabrics": [],
    "url": "https://travismathew.com/collections/mens-button-ups/products/cloud-waffle-shirt-jacket?variant=42659613409358",
    "product_id": "cloud-waffle-shirt-jacket/",
    "name": "Cloud Waffle Shirt Jacket",
    "price": 179.95,
    "sale_price": null,
    "on_sale": false,
    "images": [
      "https://cdn.shopify.com/s/files/1/0610/4629/2558/files/A42698_3DOL_1_ECOMM_ea8241f1-ae49-4c0c-82a8-176c5aab81a0.jpg"
    ],
    "badges": [],
    "sku": "cloud-waffle-shirt-jacket/"
  },
  {
    "brand": "Travis Mathew",
    "scraped_at": "2025-11-14T22:03:27.624Z",
    "is_homepage_product": false,
    "category": "Tops",
    "gender": "Men",
    "currency": "USD",
    "colors": [
      "Heather Mood Indigo"
    ],
    "sizes": [],
    "fabrics": [],
    "url": "https://travismathew.com/collections/mens-button-ups/products/deco-button-up?variant=42565167579214",
    "product_id": "deco-button-up/",
    "name": "Deco Button-Up",
    "price": 109.95,
    "sale_price": null,
    "on_sale": false,
    "images": [
      "https://cdn.shopify.com/s/files/1/0610/4629/2558/files/A40219_4HMI_1_ECOMM_648b130d-6f62-4610-9f56-ac4e2a6d9f04.jpg"
    ],
    "badges": [],
    "sku": "deco-button-up/"
  },
  {
    "brand": "Travis Mathew",
    "scraped_at": "2025-11-14T22:03:27.625Z",
    "is_homepage_product": false,
    "category": "Tops",
    "gender": "Men",
    "currency": "USD",
    "colors": [
      "White"
    ],
    "sizes": [],
    "fabrics": [],
    "url": "https://travismathew.com/collections/mens-button-ups/products/little-leary-button-up?variant=42561841791054",
    "product_id": "little-leary-button-up/",
    "name": "Little Leary Button-Up",
    "price": 139.95,
    "sale_price": null,
    "on_sale": false,
    "images": [
      "https://cdn.shopify.com/s/files/1/0610/4629/2558/files/1MY514_1WHT_1-jpg_733d4678-a2b7-46e1-9b6d-d457d7bc2f9a.jpg"
    ],
    "badges": [],
    "sku": "little-leary-button-up/"
  },
  {
    "brand": "Travis Mathew",
    "scraped_at": "2025-11-14T22:03:27.625Z",
    "is_homepage_product": false,
    "category": "Tops",
    "gender": "Men",
    "currency": "USD",
    "colors": [
      "Heather Black"
    ],
    "sizes": [],
    "fabrics": [],
    "url": "https://travismathew.com/collections/mens-button-ups/products/techwoven-grey-wind-button-up?variant=42561851719758",
    "product_id": "techwoven-grey-wind-button-up/",
    "name": "Techwoven Grey Wind Button-Up",
    "price": 99.95,
    "sale_price": null,
    "on_sale": false,
    "images": [
      "https://cdn.shopify.com/s/files/1/0610/4629/2558/files/A40214_0HBL_1_ECOMM_74763d37-1205-4c29-a488-a2bc59ddbb7e.jpg"
    ],
    "badges": [],
    "sku": "techwoven-grey-wind-button-up/"
  },
  {
    "brand": "Travis Mathew",
    "scraped_at": "2025-11-14T22:03:27.625Z",
    "is_homepage_product": false,
    "category": "Tops",
    "gender": "Men",
    "currency": "USD",
    "colors": [
      "Heather Light Grey",
      "Black",
      "Oxford Tan",
      "Dark Olive",
      "Bering Sea"
    ],
    "sizes": [],
    "fabrics": [],
    "url": "https://travismathew.com/collections/mens-button-ups/products/cloud-waffle-shirt-jacket?variant=42763778523214",
    "product_id": "cloud-waffle-shirt-jacket/",
    "name": "Cloud Waffle Shirt Jacket",
    "price": 179.95,
    "sale_price": null,
    "on_sale": false,
    "images": [
      "https://cdn.shopify.com/s/files/1/0610/4629/2558/files/A42698_0HLG_1_ECOMM_77b7c1b3-1db5-408b-8a3f-ace7447228e9.jpg"
    ],
    "badges": [],
    "sku": "cloud-waffle-shirt-jacket/"
  },
  {
    "brand": "Travis Mathew",
    "scraped_at": "2025-11-14T22:03:27.625Z",
    "is_homepage_product": false,
    "category": "Tops",
    "gender": "Men",
    "currency": "USD",
    "colors": [
      "White"
    ],
    "sizes": [],
    "fabrics": [],
    "url": "https://travismathew.com/collections/mens-button-ups/products/souvenir-city-button-up?variant=42565152014414",
    "product_id": "souvenir-city-button-up/",
    "name": "Souvenir City Button-Up",
    "price": 119.95,
    "sale_price": null,
    "on_sale": false,
    "images": [
      "https://cdn.shopify.com/s/files/1/0610/4629/2558/files/A40215_1WHT_1_ECOMM_ed791deb-82ad-46b5-95bc-b410a4b9d275.jpg"
    ],
    "badges": [],
    "sku": "souvenir-city-button-up/"
  },
  {
    "brand": "Travis Mathew",
    "scraped_at": "2025-11-14T22:03:27.625Z",
    "is_homepage_product": false,
    "category": "Tops",
    "gender": "Men",
    "currency": "USD",
    "colors": [
      "Heather Black"
    ],
    "sizes": [],
    "fabrics": [],
    "url": "https://travismathew.com/collections/mens-button-ups/products/lost-cave-button-up?variant=42561851555918",
    "product_id": "lost-cave-button-up/",
    "name": "Lost Cave Button-Up",
    "price": 109.95,
    "sale_price": null,
    "on_sale": false,
    "images": [
      "https://cdn.shopify.com/s/files/1/0610/4629/2558/files/A40211_0HBL_1_ECOMM_22fbcc2e-91b3-404c-a6b3-2f903579c594.jpg"
    ],
    "badges": [],
    "sku": "lost-cave-button-up/"
  },
  {
    "brand": "Travis Mathew",
    "scraped_at": "2025-11-14T22:03:27.626Z",
    "is_homepage_product": false,
    "category": "Tops",
    "gender": "Men",
    "currency": "USD",
    "colors": [
      "Bering Sea",
      "Black",
      "Heather Light Grey",
      "Oxford Tan",
      "Dark Olive"
    ],
    "sizes": [],
    "fabrics": [],
    "url": "https://travismathew.com/collections/mens-button-ups/products/cloud-waffle-shirt-jacket?variant=42763778883662",
    "product_id": "cloud-waffle-shirt-jacket/",
    "name": "Cloud Waffle Shirt Jacket",
    "price": 179.95,
    "sale_price": null,
    "on_sale": false,
    "images": [
      "https://cdn.shopify.com/s/files/1/0610/4629/2558/files/A42698_C0574_1_ECOMM_c7d9fd10-182c-4f95-98e4-535974e3eff8.jpg"
    ],
    "badges": [],
    "sku": "cloud-waffle-shirt-jacket/"
  },
  {
    "brand": "Travis Mathew",
    "scraped_at": "2025-11-14T22:03:27.626Z",
    "is_homepage_product": false,
    "category": "Tops",
    "gender": "Men",
    "currency": "USD",
    "colors": [
      "Quiet Shade"
    ],
    "sizes": [],
    "fabrics": [],
    "url": "https://travismathew.com/collections/mens-button-ups/products/french-riviera-button-up?variant=42561854177358",
    "product_id": "french-riviera-button-up/",
    "name": "French Riviera Button-Up",
    "price": 109.95,
    "sale_price": null,
    "on_sale": false,
    "images": [
      "https://cdn.shopify.com/s/files/1/0610/4629/2558/files/A42129_0QSH_1_ECOMM_f3863754-602a-4dbc-9555-9bcb5ac72fc3.jpg"
    ],
    "badges": [],
    "sku": "french-riviera-button-up/"
  },
  {
    "brand": "Travis Mathew",
    "scraped_at": "2025-11-14T22:03:27.626Z",
    "is_homepage_product": false,
    "category": "Tops",
    "gender": "Men",
    "currency": "USD",
    "colors": [
      "Eggshell Blue"
    ],
    "sizes": [],
    "fabrics": [],
    "url": "https://travismathew.com/collections/mens-button-ups/products/double-room-button-up?variant=42565157912654",
    "product_id": "double-room-button-up/",
    "name": "Double Room Button-Up",
    "price": 119.95,
    "sale_price": null,
    "on_sale": false,
    "images": [
      "https://cdn.shopify.com/s/files/1/0610/4629/2558/files/A40209_C0443_1_ECOMM_19f2230e-bef1-436f-ad53-58692159bc14.jpg"
    ],
    "badges": [],
    "sku": "double-room-button-up/"
  },
  {
    "brand": "Travis Mathew",
    "scraped_at": "2025-11-14T22:03:27.626Z",
    "is_homepage_product": false,
    "category": "Tops",
    "gender": "Men",
    "currency": "USD",
    "colors": [
      "Black"
    ],
    "sizes": [],
    "fabrics": [],
    "url": "https://travismathew.com/collections/mens-button-ups/products/knit-hanabata-days-button-up?variant=42425652084814",
    "product_id": "knit-hanabata-days-button-up/",
    "name": "Knit Hanabata Days Button-Up",
    "price": 119.95,
    "sale_price": null,
    "on_sale": false,
    "images": [
      "https://cdn.shopify.com/s/files/1/0610/4629/2558/files/1MAB331_0BLK_ECOMM_60441503-f4df-4b9f-b0ac-9056d67fedfb.jpg"
    ],
    "badges": [],
    "sku": "knit-hanabata-days-button-up/"
  },
  {
    "brand": "Travis Mathew",
    "scraped_at": "2025-11-14T22:03:27.626Z",
    "is_homepage_product": false,
    "category": "Tops",
    "gender": "Men",
    "currency": "USD",
    "colors": [
      "Total Eclipse"
    ],
    "sizes": [],
    "fabrics": [],
    "url": "https://travismathew.com/collections/mens-button-ups/products/techwoven-sundaze-button-up?variant=42425759236174",
    "product_id": "techwoven-sundaze-button-up/",
    "name": "Techwoven Sundaze Button-Up",
    "price": 119.95,
    "sale_price": null,
    "on_sale": false,
    "images": [
      "https://cdn.shopify.com/s/files/1/0610/4629/2558/files/A42535_4TOS_1_ECOMM_c726ff4d-6e1a-4b2b-bbfc-72c40c20be16.jpg"
    ],
    "badges": [],
    "sku": "techwoven-sundaze-button-up/"
  },
  {
    "brand": "Travis Mathew",
    "scraped_at": "2025-11-14T22:03:27.627Z",
    "is_homepage_product": false,
    "category": "Tops",
    "gender": "Men",
    "currency": "USD",
    "colors": [
      "Cameo"
    ],
    "sizes": [],
    "fabrics": [],
    "url": "https://travismathew.com/collections/mens-button-ups/products/knit-braddah-button-up?variant=42425651691598",
    "product_id": "knit-braddah-button-up/",
    "name": "Knit Braddah Button-Up",
    "price": 119.95,
    "sale_price": null,
    "on_sale": false,
    "images": [
      "https://cdn.shopify.com/s/files/1/0610/4629/2558/files/1MAB329_4CAB_P_1-JPG.jpg"
    ],
    "badges": [],
    "sku": "knit-braddah-button-up/"
  },
  {
    "brand": "Travis Mathew",
    "scraped_at": "2025-11-14T22:03:27.627Z",
    "is_homepage_product": false,
    "category": "Tops",
    "gender": "Men",
    "currency": "USD",
    "colors": [
      "Heather Sleet"
    ],
    "sizes": [],
    "fabrics": [],
    "url": "https://travismathew.com/collections/mens-button-ups/products/across-the-pond-button-up?variant=42425606078542",
    "product_id": "across-the-pond-button-up/",
    "name": "Across The Pond Button-Up",
    "price": 99.95,
    "sale_price": null,
    "on_sale": false,
    "images": [
      "https://cdn.shopify.com/s/files/1/0610/4629/2558/files/1MAA285_0HSL-jpg_a1e20ff0-fac2-4a68-9e8f-edd9ef77c831.jpg"
    ],
    "badges": [],
    "sku": "across-the-pond-button-up/"
  },
  {
    "brand": "Travis Mathew",
    "scraped_at": "2025-11-14T22:03:27.627Z",
    "is_homepage_product": false,
    "category": "Tops",
    "gender": "Men",
    "currency": "USD",
    "colors": [
      "White",
      "Copen Blue",
      "Total Eclipse"
    ],
    "sizes": [],
    "fabrics": [],
    "url": "https://travismathew.com/collections/mens-button-ups/products/the-heater-button-up?variant=42659265577038",
    "product_id": "the-heater-button-up/",
    "name": "The Heater Button-Up",
    "price": 99.95,
    "sale_price": null,
    "on_sale": false,
    "images": [
      "https://cdn.shopify.com/s/files/1/0610/4629/2558/files/A44892_1WHT_1_ECOMM_b942caf6-36d9-4db4-b925-6d95128512c2.jpg"
    ],
    "badges": [],
    "sku": "the-heater-button-up/"
  },
  {
    "brand": "Travis Mathew",
    "scraped_at": "2025-11-14T22:03:27.627Z",
    "is_homepage_product": false,
    "category": "Tops",
    "gender": "Men",
    "currency": "USD",
    "colors": [
      "Total Eclipse",
      "White",
      "Copen Blue"
    ],
    "sizes": [],
    "fabrics": [],
    "url": "https://travismathew.com/collections/mens-button-ups/products/the-heater-button-up?variant=42659266101326",
    "product_id": "the-heater-button-up/",
    "name": "The Heater Button-Up",
    "price": 99.95,
    "sale_price": null,
    "on_sale": false,
    "images": [
      "https://cdn.shopify.com/s/files/1/0610/4629/2558/files/A44892_4TOS_1_ECOMM_e5ee51e9-2a82-4a64-bb5d-a34c4f363439.jpg"
    ],
    "badges": [],
    "sku": "the-heater-button-up/"
  },
  {
    "brand": "Travis Mathew",
    "scraped_at": "2025-11-14T22:03:27.628Z",
    "is_homepage_product": false,
    "category": "Tops",
    "gender": "Men",
    "currency": "USD",
    "colors": [
      "Copen Blue",
      "White",
      "Total Eclipse"
    ],
    "sizes": [],
    "fabrics": [],
    "url": "https://travismathew.com/collections/mens-button-ups/products/the-heater-button-up?variant=42659265904718",
    "product_id": "the-heater-button-up/",
    "name": "The Heater Button-Up",
    "price": 99.95,
    "sale_price": null,
    "on_sale": false,
    "images": [
      "https://cdn.shopify.com/s/files/1/0610/4629/2558/files/A44892_4COP_1_ECOMM-jpg_412e801d-6523-4616-9782-d77ff6565e98.jpg"
    ],
    "badges": [],
    "sku": "the-heater-button-up/"
  },
  {
    "brand": "Travis Mathew",
    "scraped_at": "2025-11-14T22:03:27.628Z",
    "is_homepage_product": false,
    "category": "Tops",
    "gender": "Men",
    "currency": "USD",
    "colors": [
      "Mood Indigo/Vintage Indigo"
    ],
    "sizes": [],
    "fabrics": [],
    "url": "https://travismathew.com/collections/mens-button-ups/products/knit-featherweight-tides-button-up?variant=42561852014670",
    "product_id": "knit-featherweight-tides-button-up/",
    "name": "Knit Featherweight Tides Button-Up",
    "price": 119.95,
    "sale_price": null,
    "on_sale": false,
    "images": [
      "https://cdn.shopify.com/s/files/1/0610/4629/2558/files/A40239_4MIV_ECOMM_4c87ad76-b24d-4a10-8d59-666322b64d07.jpg"
    ],
    "badges": [],
    "sku": "knit-featherweight-tides-button-up/"
  },
  {
    "brand": "Travis Mathew",
    "scraped_at": "2025-11-14T22:03:27.628Z",
    "is_homepage_product": false,
    "category": "Tops",
    "gender": "Men",
    "currency": "USD",
    "colors": [
      "Total Eclipse/Apricot",
      "Dark Olive",
      "Birch",
      "Bering Sea/Sleet"
    ],
    "sizes": [],
    "fabrics": [],
    "url": "https://travismathew.com/collections/mens-button-ups/products/cloud-flannel-plaid-button-up?variant=42969319702606",
    "product_id": "cloud-flannel-plaid-button-up/",
    "name": "Cloud Flannel Plaid Button-Up",
    "price": 139.95,
    "sale_price": null,
    "on_sale": false,
    "images": [
      "https://cdn.shopify.com/s/files/1/0610/4629/2558/files/1MZ383_4TAP-jpg_8f220036-6dd9-4c5f-893d-c3c939d494a2.jpg"
    ],
    "badges": [],
    "sku": "cloud-flannel-plaid-button-up/"
  },
  {
    "brand": "Travis Mathew",
    "scraped_at": "2025-11-14T22:03:27.628Z",
    "is_homepage_product": false,
    "category": "Tops",
    "gender": "Men",
    "currency": "USD",
    "colors": [
      "Black"
    ],
    "sizes": [],
    "fabrics": [],
    "url": "https://travismathew.com/collections/mens-button-ups/products/photo-finish-button-up?variant=42425607389262",
    "product_id": "photo-finish-button-up/",
    "name": "Photo Finish Button-Up",
    "price": 99.95,
    "sale_price": null,
    "on_sale": false,
    "images": [
      "https://cdn.shopify.com/s/files/1/0610/4629/2558/files/1MAA352_0BLK_ECOMM-JPG_79d37899-143e-49c5-85ae-d65e9b2b2bc2.jpg"
    ],
    "badges": [],
    "sku": "photo-finish-button-up/"
  },
  {
    "brand": "Travis Mathew",
    "scraped_at": "2025-11-14T22:03:27.628Z",
    "is_homepage_product": false,
    "category": "Tops",
    "gender": "Men",
    "currency": "USD",
    "colors": [
      "Black",
      "Total Eclipse"
    ],
    "sizes": [],
    "fabrics": [],
    "url": "https://travismathew.com/collections/mens-button-ups/products/shore-of-it-button-up?variant=42659620618318",
    "product_id": "shore-of-it-button-up/",
    "name": "Shore Of It Button-Up",
    "price": 119.95,
    "sale_price": null,
    "on_sale": false,
    "images": [
      "https://cdn.shopify.com/s/files/1/0610/4629/2558/files/A45969_0BLK_1_ECOMM-jpg_b07a91aa-107d-433e-8a2e-153c6efeb886.jpg"
    ],
    "badges": [],
    "sku": "shore-of-it-button-up/"
  },
  {
    "brand": "Travis Mathew",
    "scraped_at": "2025-11-14T22:03:27.628Z",
    "is_homepage_product": false,
    "category": "Tops",
    "gender": "Men",
    "currency": "USD",
    "colors": [
      "White"
    ],
    "sizes": [],
    "fabrics": [],
    "url": "https://travismathew.com/collections/mens-button-ups/products/techwoven-acropolis-button-up?variant=42561851883598",
    "product_id": "techwoven-acropolis-button-up/",
    "name": "Techwoven Acropolis Button-Up",
    "price": 119.95,
    "sale_price": null,
    "on_sale": false,
    "images": [
      "https://cdn.shopify.com/s/files/1/0610/4629/2558/files/A40221_1WHT_ECOMM_c9a18054-ad3f-4a23-bd59-0af3f97f4fe6.jpg"
    ],
    "badges": [],
    "sku": "techwoven-acropolis-button-up/"
  },
  {
    "brand": "Travis Mathew",
    "scraped_at": "2025-11-14T22:03:27.629Z",
    "is_homepage_product": false,
    "category": "Tops",
    "gender": "Men",
    "currency": "USD",
    "colors": [
      "Total Eclipse",
      "Black"
    ],
    "sizes": [],
    "fabrics": [],
    "url": "https://travismathew.com/collections/mens-button-ups/products/shore-of-it-button-up?variant=42659620847694",
    "product_id": "shore-of-it-button-up/",
    "name": "Shore Of It Button-Up",
    "price": 119.95,
    "sale_price": null,
    "on_sale": false,
    "images": [
      "https://cdn.shopify.com/s/files/1/0610/4629/2558/files/A45969_4TOS_1_ECOMM-jpg_aaed19e2-9556-438a-b37d-f86e544a7fca.jpg"
    ],
    "badges": [],
    "sku": "shore-of-it-button-up/"
  },
  {
    "brand": "Travis Mathew",
    "scraped_at": "2025-11-14T22:03:27.629Z",
    "is_homepage_product": false,
    "category": "Tops",
    "gender": "Men",
    "currency": "USD",
    "colors": [
      "Micro Chip"
    ],
    "sizes": [],
    "fabrics": [],
    "url": "https://travismathew.com/collections/mens-button-ups/products/light-map-button-up?variant=42425740034126",
    "product_id": "light-map-button-up/",
    "name": "Light Map Button-Up",
    "price": 119.95,
    "sale_price": null,
    "on_sale": false,
    "images": [
      "https://cdn.shopify.com/s/files/1/0610/4629/2558/files/A40222_0MCR_1_ECOMM_e970b0ab-9a3b-4c84-8958-4e3ce831ace3.jpg"
    ],
    "badges": [],
    "sku": "light-map-button-up/"
  },
  {
    "brand": "Travis Mathew",
    "scraped_at": "2025-11-14T22:03:27.629Z",
    "is_homepage_product": false,
    "category": "Tops",
    "gender": "Men",
    "currency": "USD",
    "colors": [
      "Heather Violet Storm"
    ],
    "sizes": [],
    "fabrics": [],
    "url": "https://travismathew.com/collections/mens-button-ups/products/knit-trip-to-the-city-button-up?variant=42567408648270",
    "product_id": "knit-trip-to-the-city-button-up/",
    "name": "Knit Trip To The City Button-Up",
    "price": 119.95,
    "sale_price": null,
    "on_sale": false,
    "images": [
      "https://cdn.shopify.com/s/files/1/0610/4629/2558/files/A40245_I0093_ECOMM_0afb0d97-e827-4eeb-bd49-889d5d3f002f.jpg"
    ],
    "badges": [],
    "sku": "knit-trip-to-the-city-button-up/"
  },
  {
    "brand": "Travis Mathew",
    "scraped_at": "2025-11-14T22:03:27.629Z",
    "is_homepage_product": false,
    "category": "Tops",
    "gender": "Men",
    "currency": "USD",
    "colors": [
      "White/Quiet Harbor"
    ],
    "sizes": [],
    "fabrics": [],
    "url": "https://travismathew.com/collections/mens-button-ups/products/the-thick-of-it-button-up?variant=42561818886222",
    "product_id": "the-thick-of-it-button-up/",
    "name": "The Thick Of It Button-Up",
    "price": 99.95,
    "sale_price": null,
    "on_sale": false,
    "images": [
      "https://cdn.shopify.com/s/files/1/0610/4629/2558/files/1MAA275_1WQH_ECOMM-JPG_a6206b66-8e7f-4dee-9a72-2091c1c1894c.jpg"
    ],
    "badges": [],
    "sku": "the-thick-of-it-button-up/"
  },
  {
    "brand": "Travis Mathew",
    "scraped_at": "2025-11-14T22:03:27.629Z",
    "is_homepage_product": false,
    "category": "Tops",
    "gender": "Men",
    "currency": "USD",
    "colors": [
      "Black",
      "White"
    ],
    "sizes": [],
    "fabrics": [],
    "url": "https://travismathew.com/collections/mens-button-ups/products/mist-on-the-lake-button-up?variant=42969297420366",
    "product_id": "mist-on-the-lake-button-up/",
    "name": "Mist On The Lake Button-Up",
    "price": 99.95,
    "sale_price": null,
    "on_sale": false,
    "images": [
      "https://cdn.shopify.com/s/files/1/0610/4629/2558/files/1MAA268_0BLK_ECOMM-JPG_ce68a3a9-7da5-4811-a3bb-4034b0c4d497.jpg"
    ],
    "badges": [],
    "sku": "mist-on-the-lake-button-up/"
  },
  {
    "brand": "Travis Mathew",
    "scraped_at": "2025-11-14T22:03:27.629Z",
    "is_homepage_product": false,
    "category": "Tops",
    "gender": "Men",
    "currency": "USD",
    "colors": [
      "White"
    ],
    "sizes": [],
    "fabrics": [],
    "url": "https://travismathew.com/collections/mens-button-ups/products/techwoven-board-battle-button-up?variant=42425756450894",
    "product_id": "techwoven-board-battle-button-up/",
    "name": "Techwoven Board Battle Button-Up",
    "price": 109.95,
    "sale_price": null,
    "on_sale": false,
    "images": [
      "https://cdn.shopify.com/s/files/1/0610/4629/2558/files/A42463_1WHT_1_ECOMM_dd35ecdf-75b4-4020-ae01-0919604aef58.jpg"
    ],
    "badges": [],
    "sku": "techwoven-board-battle-button-up/"
  },
  {
    "brand": "Travis Mathew",
    "scraped_at": "2025-11-14T22:03:27.630Z",
    "is_homepage_product": false,
    "category": "Tops",
    "gender": "Men",
    "currency": "USD",
    "colors": [
      "Black"
    ],
    "sizes": [],
    "fabrics": [],
    "url": "https://travismathew.com/collections/mens-button-ups/products/knit-gravitation-button-up?variant=42561854308430",
    "product_id": "knit-gravitation-button-up/",
    "name": "Knit Gravitation Button-Up",
    "price": 119.95,
    "sale_price": null,
    "on_sale": false,
    "images": [
      "https://cdn.shopify.com/s/files/1/0610/4629/2558/files/A42377_0BLK_ECOMM_1d4e6e01-1a57-4297-a36b-75a5894621e3.jpg"
    ],
    "badges": [],
    "sku": "knit-gravitation-button-up/"
  },
  {
    "brand": "Travis Mathew",
    "scraped_at": "2025-11-14T22:03:27.630Z",
    "is_homepage_product": false,
    "category": "Tops",
    "gender": "Men",
    "currency": "USD",
    "colors": [
      "White"
    ],
    "sizes": [],
    "fabrics": [],
    "url": "https://travismathew.com/collections/mens-button-ups/products/knit-flourish-button-up?variant=42425741279310",
    "product_id": "knit-flourish-button-up/",
    "name": "Knit Flourish Button-Up",
    "price": 119.95,
    "sale_price": null,
    "on_sale": false,
    "images": [
      "https://cdn.shopify.com/s/files/1/0610/4629/2558/files/A40244_1WHT_ECOMM_7097a9d5-e0d7-4ef9-8dd8-e03f84d19346.jpg"
    ],
    "badges": [],
    "sku": "knit-flourish-button-up/"
  },
  {
    "brand": "Travis Mathew",
    "scraped_at": "2025-11-14T22:03:27.630Z",
    "is_homepage_product": false,
    "category": "Tops",
    "gender": "Men",
    "currency": "USD",
    "colors": [
      "White",
      "Black"
    ],
    "sizes": [],
    "fabrics": [],
    "url": "https://travismathew.com/collections/mens-button-ups/products/poolside-pitcher-button-up?variant=42659273310286",
    "product_id": "poolside-pitcher-button-up/",
    "name": "Poolside Pitcher Button-Up",
    "price": 119.95,
    "sale_price": null,
    "on_sale": false,
    "images": [
      "https://cdn.shopify.com/s/files/1/0610/4629/2558/files/A46006_1WHT_1_ECOMM_f0eca8f3-8737-4231-ab1c-63a50c8b69dd.jpg"
    ],
    "badges": [],
    "sku": "poolside-pitcher-button-up/"
  },
  {
    "brand": "Travis Mathew",
    "scraped_at": "2025-11-14T22:03:27.630Z",
    "is_homepage_product": false,
    "category": "Tops",
    "gender": "Men",
    "currency": "USD",
    "colors": [
      "Black",
      "White"
    ],
    "sizes": [],
    "fabrics": [],
    "url": "https://travismathew.com/collections/mens-button-ups/products/poolside-pitcher-button-up?variant=42659273113678",
    "product_id": "poolside-pitcher-button-up/",
    "name": "Poolside Pitcher Button-Up",
    "price": 119.95,
    "sale_price": null,
    "on_sale": false,
    "images": [
      "https://cdn.shopify.com/s/files/1/0610/4629/2558/files/A46006_0BLK_1_ECOMM_82c752b3-421a-471c-8d0f-376e9e8fd741.jpg"
    ],
    "badges": [],
    "sku": "poolside-pitcher-button-up/"
  },
  {
    "brand": "Travis Mathew",
    "scraped_at": "2025-11-14T22:03:27.630Z",
    "is_homepage_product": false,
    "category": "Tops",
    "gender": "Men",
    "currency": "USD",
    "colors": [
      "Oxford Tan"
    ],
    "sizes": [],
    "fabrics": [],
    "url": "https://travismathew.com/collections/mens-button-ups/products/cloud-flannel-stripe-button-up?variant=42425719488590",
    "product_id": "cloud-flannel-stripe-button-up/",
    "name": "Cloud Flannel Stripe Button-Up",
    "price": 139.95,
    "sale_price": null,
    "on_sale": false,
    "images": [
      "https://cdn.shopify.com/s/files/1/0610/4629/2558/files/1MZ378_2OFT_ECOMM-JPG_b0678288-fce3-4511-98b8-fc407c496520.jpg"
    ],
    "badges": [],
    "sku": "cloud-flannel-stripe-button-up/"
  },
  {
    "brand": "Travis Mathew",
    "scraped_at": "2025-11-14T22:03:27.630Z",
    "is_homepage_product": false,
    "category": "Tops",
    "gender": "Men",
    "currency": "USD",
    "colors": [
      "Captains Blue"
    ],
    "sizes": [],
    "fabrics": [],
    "url": "https://travismathew.com/collections/mens-button-ups/products/per-aspera-button-up?variant=42425740329038",
    "product_id": "per-aspera-button-up/",
    "name": "Per Aspera Button-Up",
    "price": 109.95,
    "sale_price": null,
    "on_sale": false,
    "images": [
      "https://cdn.shopify.com/s/files/1/0610/4629/2558/files/A40223_C0438_ECOMM-jpg_9c379e44-8d52-4f51-bad0-3ad9b6909fec.jpg"
    ],
    "badges": [],
    "sku": "per-aspera-button-up/"
  },
  {
    "brand": "Travis Mathew",
    "scraped_at": "2025-11-14T22:03:27.631Z",
    "is_homepage_product": false,
    "category": "Tops",
    "gender": "Men",
    "currency": "USD",
    "colors": [
      "Dark Olive"
    ],
    "sizes": [],
    "fabrics": [],
    "url": "https://travismathew.com/collections/mens-button-ups/products/evening-bonfire-button-up?variant=42425650151502",
    "product_id": "evening-bonfire-button-up/",
    "name": "Evening Bonfire Button-Up",
    "price": 139.95,
    "sale_price": null,
    "on_sale": false,
    "images": [
      "https://cdn.shopify.com/s/files/1/0610/4629/2558/files/1MAB304_3DOL_1-jpg_859b7340-8f34-45cd-98cc-cb928d5745d5.jpg"
    ],
    "badges": [],
    "sku": "evening-bonfire-button-up/"
  }
]